zeno_evals/__init__.py
zeno_evals/__main__.py
zeno_evals/main.py
zeno_evals-0.1.10.dist-info/LICENSE.md
zeno_evals-0.1.10.dist-info/WHEEL
zeno_evals-0.1.10.dist-info/entry_points.txt
zeno_evals-0.1.10.dist-info/METADATA
zeno_evals-0.1.10.dist-info/RECORD
