Metadata-Version: 2.1
Name: zeno-evals
Version: 0.1.10
Summary: Visualize OpenAI evals with Zeno
Author: Alex Cabrera
Author-email: alex.cabrera@gmail.com
Requires-Python: >=3.9,<=3.11
Classifier: Programming Language :: Python :: 3
Classifier: Programming Language :: Python :: 3.9
Classifier: Programming Language :: Python :: 3.10
Classifier: Programming Language :: Python :: 3.11
Requires-Dist: fire (>=0.5.0,<0.6.0)
Requires-Dist: zenoml (>=0.4.10,<0.5.0)
